README.md
setup.py
finkelsteinlabpalette.egg-info/PKG-INFO
finkelsteinlabpalette.egg-info/SOURCES.txt
finkelsteinlabpalette.egg-info/dependency_links.txt
finkelsteinlabpalette.egg-info/top_level.txt
flabpal/__init__.py
flabpal/colors.py
flabpal/microscope.py