Metadata-Version: 1.1
Name: finkelsteinlabpalette
Version: 1.2.1
Summary: Finkelstein Lab standard color palette
Home-page: https://github.com/jimrybarski/finkelstein-lab-palette
Author: Jim Rybarski
Author-email: jim@rybarski.com
License: UNKNOWN
Download-URL: https://github.com/jimrybarski/finkelstein-lab-palette/tarball/1.2.1
Keywords: color,palette,colorblind
Platform: UNKNOWN
Classifier: Development Status :: 4 - Beta
Classifier: Intended Audience :: Science/Research
Classifier: License :: Freely Distributable
Classifier: License :: OSI Approved :: MIT License
Classifier: Programming Language :: Python :: 2
Classifier: Programming Language :: Python :: 3
Classifier: Topic :: Scientific/Engineering :: Visualization
Classifier: Natural Language :: English
